fastrk/__init__.py
fastrk/bt.py
fastrk/bt_6_5_8_M.py
fastrk/bt_8_7_13_M.py
fastrk/bt_8_9_16.py
fastrk/ev_generator.py
fastrk/rk_base.py
fastrk/rk_base2.py
fastrk/rk_generator.py
fastrk-0.0.5.dist-info/LICENCE
fastrk-0.0.5.dist-info/METADATA
fastrk-0.0.5.dist-info/WHEEL
fastrk-0.0.5.dist-info/top_level.txt
fastrk-0.0.5.dist-info/RECORD
