Metadata-Version: 2.1
Name: fastrk
Version: 0.0.5
Summary: FastRK, a generator of fast jit-compiled code for ODE propagation by ERK methods with adaptive step and events
Home-page: https://github.com/BoberSA/fastrk
Author: Bober S.A.
Author-email: stas.bober@gmail.com
License: MIT
Platform: UNKNOWN
Classifier: Development Status :: 3 - Alpha
Classifier: Topic :: Scientific/Engineering
Classifier: Topic :: Scientific/Engineering :: Mathematics
Classifier: Topic :: Scientific/Engineering :: Physics
Classifier: Programming Language :: Python :: 3
Classifier: License :: OSI Approved :: MIT License
Classifier: Operating System :: OS Independent
Requires-Python: >=3.7
Requires-Dist: numba (>=0.51.2)
Requires-Dist: numpy (>=1.19.2)
Requires-Dist: sympy (>=1.8)
Requires-Dist: scipy (>=1.2)
